<annotation><folder>images</folder><filename>cherry-leaves-e1335624103663_jpg.rf.8719eed3acb65218105a7f9f1803cc77.jpg</filename><path>PlantDoc.v1-resize-416x416.yolov5pytorch/train/images</path><source><database>Unknown</database></source><size><width>416</width><height>416</height><depth>3</depth></size><segmented>0</segmented><object><name>Cherry leaf</name><pose>Unspecified</pose><truncated>0</truncated><difficult>0</difficult><bndbox><xmin>225</xmin><ymin>1</ymin><xmax>352</xmax><ymax>168</ymax></bndbox></object><object><name>Cherry leaf</name><pose>Unspecified</pose><truncated>0</truncated><difficult>0</difficult><bndbox><xmin>125</xmin><ymin>221</ymin><xmax>282</xmax><ymax>415</ymax></bndbox></object><object><name>Cherry leaf</name><pose>Unspecified</pose><truncated>0</truncated><difficult>0</difficult><bndbox><xmin>0</xmin><ymin>144</ymin><xmax>170</xmax><ymax>232</ymax></bndbox></object><object><name>Cherry leaf</name><pose>Unspecified</pose><truncated>0</truncated><difficult>0</difficult><bndbox><xmin>0</xmin><ymin>58</ymin><xmax>158</xmax><ymax>142</ymax></bndbox></object><object><name>Cherry leaf</name><pose>Unspecified</pose><truncated>0</truncated><difficult>0</difficult><bndbox><xmin>83</xmin><ymin>40</ymin><xmax>213</xmax><ymax>131</ymax></bndbox></object></annotation>