<annotation><folder>images</folder><filename>depositphotos_164701744-stock-photo-closeup-of-strawberry-leaves_jpg.rf.93f124de88cc7a35d1ae5903bfeb6033.jpg</filename><path>PlantDoc.v1-resize-416x416.yolov5pytorch/train/images</path><source><database>Unknown</database></source><size><width>416</width><height>416</height><depth>3</depth></size><segmented>0</segmented><object><name>Strawberry leaf</name><pose>Unspecified</pose><truncated>0</truncated><difficult>0</difficult><bndbox><xmin>66</xmin><ymin>169</ymin><xmax>236</xmax><ymax>330</ymax></bndbox></object><object><name>Strawberry leaf</name><pose>Unspecified</pose><truncated>0</truncated><difficult>0</difficult><bndbox><xmin>52</xmin><ymin>43</ymin><xmax>236</xmax><ymax>194</ymax></bndbox></object><object><name>Strawberry leaf</name><pose>Unspecified</pose><truncated>0</truncated><difficult>0</difficult><bndbox><xmin>212</xmin><ymin>142</ymin><xmax>368</xmax><ymax>328</ymax></bndbox></object></annotation>